ds/__init__.py
ds/ds_list.py
ds/ds_queue.py
ds/ds_stack.py
pure_datastructures-0.0.3.dist-info/AUTHORS
pure_datastructures-0.0.3.dist-info/LICENSE
pure_datastructures-0.0.3.dist-info/METADATA
pure_datastructures-0.0.3.dist-info/WHEEL
pure_datastructures-0.0.3.dist-info/top_level.txt
pure_datastructures-0.0.3.dist-info/RECORD
